code_to_txt/__init__.py
code_to_txt/cli.py
code_to_txt/code_to_txt.py
code_to_txt-0.1.0.dist-info/METADATA
code_to_txt-0.1.0.dist-info/WHEEL
code_to_txt-0.1.0.dist-info/entry_points.txt
code_to_txt-0.1.0.dist-info/RECORD
