Metadata-Version: 2.4
Name: code-to-txt
Version: 0.1.0
Summary: Convert code files to a single text file for LLM consumption
License: MIT
Author: Andrii Sonsiadlo
Author-email: andrii.sonsiadlo@gmail.com
Requires-Python: >=3.10
Classifier: License :: OSI Approved :: MIT License
Classifier: Programming Language :: Python :: 3
Classifier: Programming Language :: Python :: 3.10
Classifier: Programming Language :: Python :: 3.11
Classifier: Programming Language :: Python :: 3.12
Classifier: Programming Language :: Python :: 3.13
Classifier: Programming Language :: Python :: 3.14
Requires-Dist: click (>=8.3.1,<9.0.0)
Requires-Dist: gitpython (>=3.1.46,<4.0.0)
Requires-Dist: pathspec (>=1.0.4,<2.0.0)
